lithium_enrichment_cost_calculator/__init__.py
lithium_enrichment_cost_calculator/core.py
lithium_enrichment_cost_calculator-0.1.0.dist-info/LICENSE
lithium_enrichment_cost_calculator-0.1.0.dist-info/METADATA
lithium_enrichment_cost_calculator-0.1.0.dist-info/WHEEL
lithium_enrichment_cost_calculator-0.1.0.dist-info/top_level.txt
lithium_enrichment_cost_calculator-0.1.0.dist-info/RECORD
