Metadata-Version: 2.1
Name: lithium-enrichment-cost-calculator
Version: 0.1.0
Summary: Create 3D fusion reactor CAD models based on input parameters
Home-page: https://github.com/fusion-energy/lithium_enrichment_cost_calculator
Author: The lithium_enrichment_cost_calculator Development Team
Author-email: mail@jshimwell.com
License: UNKNOWN
Platform: UNKNOWN
Classifier: Natural Language :: English
Classifier: Topic :: Scientific/Engineering
Classifier: Programming Language :: Python :: 3
Classifier: Programming Language :: Python :: 3.6
Classifier: Programming Language :: Python :: 3.7
Classifier: Programming Language :: Python :: 3.8
Classifier: Programming Language :: Python :: 3.9
Classifier: License :: OSI Approved :: MIT License
Classifier: Operating System :: OS Independent
Requires-Python: >=3.6
License-File: LICENSE
Requires-Dist: numpy
